ruleminer/__init__.py
ruleminer/const.py
ruleminer/encodings.py
ruleminer/evaluator.py
ruleminer/generate_tests.py
ruleminer/grammar.py
ruleminer/metrics.py
ruleminer/pandas_parser.py
ruleminer/parser.py
ruleminer/ruleminer.py
ruleminer/tolerance.py
ruleminer/utils.py
ruleminer-1.0.0.dist-info/LICENSE
ruleminer-1.0.0.dist-info/METADATA
ruleminer-1.0.0.dist-info/WHEEL
ruleminer-1.0.0.dist-info/RECORD
