Metadata-Version: 2.3
Name: ruleminer
Version: 1.0.0
Summary: Python package to mine association rules in datasets
License: MIT/X
Keywords: association rules,pandas
Author: Willem Jan Willemse
Author-email: w.j.willemse@freedom.nl
Requires-Python: >=3.9,<3.13
Classifier: Development Status :: 3 - Alpha
Classifier: License :: OSI Approved :: MIT License
Classifier: Natural Language :: English
Classifier: Operating System :: OS Independent
Classifier: Programming Language :: Python
Classifier: Programming Language :: Python :: 3.8
Classifier: Programming Language :: Python :: 3.9
Classifier: Programming Language :: Python :: 3.10
Classifier: Programming Language :: Python :: 3.11
Classifier: Programming Language :: Python :: 3.12
Requires-Dist: numpy
Requires-Dist: pandas
Requires-Dist: pyparsing (>=3.0.0)
Requires-Dist: regex
Requires-Dist: scikit-learn
Project-URL: Documentation, https://ruleminer.readthedocs.io/en/latest/
Project-URL: Homepage, https://github.com/DeNederlandscheBank/ruleminer
Project-URL: Repository, https://github.com/DeNederlandscheBank/ruleminer
